metemcyber/__init__.py
metemcyber/cli/__init__.py
metemcyber/cli/cli.py
metemcyber/cli/constants.py
metemcyber/cli/source_of_truth.yml
metemcyber/cli/workflow.yml
metemcyber/cli/app_dir/external-links.json
metemcyber/cli/app_dir/misp/misp.ini
metemcyber/cli/app_dir/workspace.ganache/config.ini
metemcyber/cli/app_dir/workspace.pricom-mainnet/config.ini
metemcyber/core/__init__.py
metemcyber/core/logger.py
metemcyber/core/multi_solver.py
metemcyber/core/multi_solver_cli.py
metemcyber/core/ngrok.py
metemcyber/core/plugin.py
metemcyber/core/seeker.py
metemcyber/core/solver.py
metemcyber/core/util.py
metemcyber/core/webhook.py
metemcyber/core/bc/__init__.py
metemcyber/core/bc/account.py
metemcyber/core/bc/address_group.py
metemcyber/core/bc/broker.py
metemcyber/core/bc/catalog.py
metemcyber/core/bc/catalog_manager.py
metemcyber/core/bc/contract.py
metemcyber/core/bc/cti_broker.py
metemcyber/core/bc/cti_catalog.py
metemcyber/core/bc/cti_operator.py
metemcyber/core/bc/cti_token.py
metemcyber/core/bc/erc1820.tx.raw
metemcyber/core/bc/ether.py
metemcyber/core/bc/eventlistener.py
metemcyber/core/bc/metemcyber_util.py
metemcyber/core/bc/operator.py
metemcyber/core/bc/token.py
metemcyber/core/bc/util.py
metemcyber/core/bc/wallet.py
metemcyber/core/bc/contracts_data/AddressGroup.combined.json
metemcyber/core/bc/contracts_data/AddressGroup.combined.json-0
metemcyber/core/bc/contracts_data/CTIBroker.combined.json
metemcyber/core/bc/contracts_data/CTIBroker.combined.json-0
metemcyber/core/bc/contracts_data/CTICatalog.combined.json
metemcyber/core/bc/contracts_data/CTICatalog.combined.json-0
metemcyber/core/bc/contracts_data/CTICatalog.combined.json-1
metemcyber/core/bc/contracts_data/CTIOperator.combined.json
metemcyber/core/bc/contracts_data/CTIOperator.combined.json-0
metemcyber/core/bc/contracts_data/CTIOperator.combined.json-1
metemcyber/core/bc/contracts_data/CTIToken.combined.json
metemcyber/core/bc/contracts_data/CTIToken.combined.json-0
metemcyber-0.6.0.dist-info/LICENSE
metemcyber-0.6.0.dist-info/METADATA
metemcyber-0.6.0.dist-info/WHEEL
metemcyber-0.6.0.dist-info/entry_points.txt
metemcyber-0.6.0.dist-info/top_level.txt
metemcyber-0.6.0.dist-info/RECORD
