Metadata-Version: 2.1
Name: metemcyber
Version: 0.6.0
Summary: Decentralized Cyber Threat Intelligence Kaizen Framework.
Home-page: https://github.com/nttcom/metemcyber
Author: NTT Communications Corporation
Author-email: metemcyber@ntt.com
License: UNKNOWN
Project-URL: Source, https://github.com/nttcom/metemcyber/
Project-URL: Bug Tracker, https://github.com/nttcom/metemcyber/issues
Project-URL: Documentation, http://metemcyber.readthedocs.org/
Keywords: cti,cyber,threat,intelligence,data pipelines,ethereum
Platform: UNKNOWN
Classifier: Development Status :: 3 - Alpha
Classifier: Intended Audience :: Developers
Classifier: Topic :: Security
Classifier: License :: OSI Approved :: Apache Software License
Classifier: Programming Language :: Python :: 3
Classifier: Programming Language :: Python :: 3.8
Requires-Python: >=3.8
License-File: LICENSE
Requires-Dist: web3
Requires-Dist: flask
Requires-Dist: pymisp
Requires-Dist: typer
Requires-Dist: psutil
Requires-Dist: cryptography
Requires-Dist: eth-account
Requires-Dist: PyYAML
Requires-Dist: google-cloud-storage
Provides-Extra: cli
Requires-Dist: kedro ; extra == 'cli'
Requires-Dist: kedro-viz ; extra == 'cli'
